pyomorfi/__init__.py
pyomorfi/omorfi.analyse.kfst
pyomorfi/omorfi.describe.kfst
pyomorfi/omorfi.generate.kfst
pyomorfi/omorfi.segment.kfst
pyomorfi/omorfi/__init__.py
pyomorfi/omorfi/analyser.py
pyomorfi/omorfi/analysis.py
pyomorfi/omorfi/doc.py
pyomorfi/omorfi/error_logging.py
pyomorfi/omorfi/generator.py
pyomorfi/omorfi/guesser.py
pyomorfi/omorfi/hfst.py
pyomorfi/omorfi/hyphenator.py
pyomorfi/omorfi/labelsegmenter.py
pyomorfi/omorfi/lemmatiser.py
pyomorfi/omorfi/omorfi.py
pyomorfi/omorfi/segmenter.py
pyomorfi/omorfi/settings.py
pyomorfi/omorfi/string_manglers.py
pyomorfi/omorfi/token.py
pyomorfi/omorfi/tokeniser.py
pyomorfi/omorfi/disamparsulate/__init__.py
pyomorfi/omorfi/disamparsulate/disamparsulator.py
pyomorfi/omorfi/disamparsulate/evidence.py
pyomorfi/omorfi/disamparsulate/matcher.py
pyomorfi/omorfi/entryguessing/__init__.py
pyomorfi/omorfi/entryguessing/gradation.py
pyomorfi/omorfi/entryguessing/guess_feats.py
pyomorfi/omorfi/entryguessing/guess_new_class.py
pyomorfi/omorfi/entryguessing/parse_csv_data.py
pyomorfi/omorfi/entryguessing/plurale_tantum.py
pyomorfi/omorfi/entryguessing/stub.py
pyomorfi/omorfi/entryguessing/wordmap.py
pyomorfi/omorfi/formats/__init__.py
pyomorfi/omorfi/formats/apertium_formatter.py
pyomorfi/omorfi/formats/experimental_xml_formatter.py
pyomorfi/omorfi/formats/fileformats.py
pyomorfi/omorfi/formats/formatter.py
pyomorfi/omorfi/formats/ftb3_formatter.py
pyomorfi/omorfi/formats/giella_formatter.py
pyomorfi/omorfi/formats/kotus_sanalista_formatter.py
pyomorfi/omorfi/formats/labeled_segments_formatter.py
pyomorfi/omorfi/formats/lexc_formatter.py
pyomorfi/omorfi/formats/monodix_formatter.py
pyomorfi/omorfi/formats/no_tags_formatter.py
pyomorfi/omorfi/formats/omor_formatter.py
pyomorfi/omorfi/formats/regex_formatter.py
pyomorfi/omorfi/formats/tdt_formatter.py
pyomorfi/omorfi/formats/twolc_formatter.py
pyomorfi-1.0.1.dist-info/LICENSE
pyomorfi-1.0.1.dist-info/METADATA
pyomorfi-1.0.1.dist-info/WHEEL
pyomorfi-1.0.1.dist-info/top_level.txt
pyomorfi-1.0.1.dist-info/RECORD
