Metadata-Version: 2.1
Name: pyomorfi
Version: 1.0.1
Summary: A pure-python implementation of the Omorfi library that provides Finnish morphological analysis
Home-page: https://github.com/fergusq/fst-python
Author: Iikka Hauhio
Author-email: iikka.hauhio@helsinki.fi
License: GNU GPLv3
Project-URL: Bug Tracker, https://github.com/fergusq/fst-python/issues
Keywords: finnish nlp morphology
Classifier: License :: OSI Approved :: GNU General Public License v3 (GPLv3)
Classifier: Programming Language :: Python
Classifier: Programming Language :: Python :: 3
Requires-Python: >=3.8
License-File: LICENSE
Requires-Dist: kfst
